{"ObjectStates":[{"Name":"Deck","Nickname":"Deck Não-Locais","Description":"","LuaScript":"","Transform":{"posX":0,"posY":0,"posZ":0,"rotX":0,"rotY":180,"rotZ":180,"scaleX":1.13636363636,"scaleY":1,"scaleZ":1.13636363636},"DeckIDs":[100,101,102,103,104,105,106,107,108,109,110,111,112,113,114,115,116,117,118,119,120,121,122,123,124,125,126,127,128,129,130,131,132,133,134,135,136,137,138,139,140,141,142,143,144,145,146,147,200,201,202,203,204,205,206,207,208,209,210,211,212,213,214,215,216,217,218,219,220,221,222,223,224,225,226,227,228,229,230,231,232,233,234,235,236,237,238,239,240,241,242,243,244,245,246,247,300,301,302,303,304,305,306,307,308,309,310,311,312,313,314,315,316,317,318,319,320,321,322],"ContainedObjects":[{"CardID":100,"Name":"card","Nickname":"Percyllian, Herói de Guerra","Description":"","Transform":{"posX":0,"posY":0,"posZ":0,"rotX":0,"rotY":180,"rotZ":180,"scaleX":1,"scaleY":1,"scaleZ":1}},{"CardID":101,"Name":"card","Nickname":"Percyllian, o Pardal","Transform":{"posX":0,"posY":0,"posZ":0,"rotX":0,"rotY":180,"rotZ":180,"scaleX":1,"scaleY":1,"scaleZ":1}},{"CardID":102,"Name":"card","Nickname":"Duergar Highborne, Clamor do Povo","Transform":{"posX":0,"posY":0,"posZ":0,"rotX":0,"rotY":180,"rotZ":180,"scaleX":1,"scaleY":1,"scaleZ":1}},{"CardID":103,"Name":"card","Nickname":"Brennan Ferrotorque, Chama em Marcha","Transform":{"posX":0,"posY":0,"posZ":0,"rotX":0,"rotY":180,"rotZ":180,"scaleX":1,"scaleY":1,"scaleZ":1}},{"CardID":104,"Name":"card","Nickname":"Torre Viva da Guarda-Sol","Transform":{"posX":0,"posY":0,"posZ":0,"rotX":0,"rotY":180,"rotZ":180,"scaleX":1,"scaleY":1,"scaleZ":1}},{"CardID":105,"Name":"card","Nickname":"Capitão Guarda-Sol","Transform":{"posX":0,"posY":0,"posZ":0,"rotX":0,"rotY":180,"rotZ":180,"scaleX":1,"scaleY":1,"scaleZ":1}},{"CardID":106,"Name":"card","Nickname":"Jorah Veihl, Pastor da Tempestade","Transform":{"posX":0,"posY":0,"posZ":0,"rotX":0,"rotY":180,"rotZ":180,"scaleX":1,"scaleY":1,"scaleZ":1}},{"CardID":107,"Name":"card","Nickname":"Sem Rosto, Sussurro das Guildas","Transform":{"posX":0,"posY":0,"posZ":0,"rotX":0,"rotY":180,"rotZ":180,"scaleX":1,"scaleY":1,"scaleZ":1}},{"CardID":108,"Name":"card","Nickname":"Percyllian, Líder Improvisado","Transform":{"posX":0,"posY":0,"posZ":0,"rotX":0,"rotY":180,"rotZ":180,"scaleX":1,"scaleY":1,"scaleZ":1}},{"CardID":109,"Name":"card","Nickname":"Vel, o \"Óptico\"","Transform":{"posX":0,"posY":0,"posZ":0,"rotX":0,"rotY":180,"rotZ":180,"scaleX":1,"scaleY":1,"scaleZ":1}},{"CardID":110,"Name":"card","Nickname":"Merion Drel, A Teia do Sem-Rosto","Transform":{"posX":0,"posY":0,"posZ":0,"rotX":0,"rotY":180,"rotZ":180,"scaleX":1,"scaleY":1,"scaleZ":1}},{"CardID":111,"Name":"card","Nickname":"Vigia do Olho Escondido","Transform":{"posX":0,"posY":0,"posZ":0,"rotX":0,"rotY":180,"rotZ":180,"scaleX":1,"scaleY":1,"scaleZ":1}},{"CardID":112,"Name":"card","Nickname":"Infiltrador de Emanação","Transform":{"posX":0,"posY":0,"posZ":0,"rotX":0,"rotY":180,"rotZ":180,"scaleX":1,"scaleY":1,"scaleZ":1}},{"CardID":113,"Name":"card","Nickname":"Mensageiro da Torre Branca","Transform":{"posX":0,"posY":0,"posZ":0,"rotX":0,"rotY":180,"rotZ":180,"scaleX":1,"scaleY":1,"scaleZ":1}},{"CardID":114,"Name":"card","Nickname":"Guarda-Sol do Primeiro Portão","Transform":{"posX":0,"posY":0,"posZ":0,"rotX":0,"rotY":180,"rotZ":180,"scaleX":1,"scaleY":1,"scaleZ":1}},{"CardID":115,"Name":"card","Nickname":"Guarda-Sol da Porta de Bronze","Transform":{"posX":0,"posY":0,"posZ":0,"rotX":0,"rotY":180,"rotZ":180,"scaleX":1,"scaleY":1,"scaleZ":1}},{"CardID":116,"Name":"card","Nickname":"Odde Brightwill, Voz da Razão","Transform":{"posX":0,"posY":0,"posZ":0,"rotX":0,"rotY":180,"rotZ":180,"scaleX":1,"scaleY":1,"scaleZ":1}},{"CardID":117,"Name":"card","Nickname":"Agente de Comunicação de Campanha","Transform":{"posX":0,"posY":0,"posZ":0,"rotX":0,"rotY":180,"rotZ":180,"scaleX":1,"scaleY":1,"scaleZ":1}},{"CardID":118,"Name":"card","Nickname":"Porta-Estandarte do 3º Batalhão","Transform":{"posX":0,"posY":0,"posZ":0,"rotX":0,"rotY":180,"rotZ":180,"scaleX":1,"scaleY":1,"scaleZ":1}},{"CardID":119,"Name":"card","Nickname":"Instrutor da 7ª Companhia","Transform":{"posX":0,"posY":0,"posZ":0,"rotX":0,"rotY":180,"rotZ":180,"scaleX":1,"scaleY":1,"scaleZ":1}},{"CardID":120,"Name":"card","Nickname":"Sacerdote do Dragão de Prata","Transform":{"posX":0,"posY":0,"posZ":0,"rotX":0,"rotY":180,"rotZ":180,"scaleX":1,"scaleY":1,"scaleZ":1}},{"CardID":121,"Name":"card","Nickname":"Espião da Muralha Interna","Transform":{"posX":0,"posY":0,"posZ":0,"rotX":0,"rotY":180,"rotZ":180,"scaleX":1,"scaleY":1,"scaleZ":1}},{"CardID":122,"Name":"card","Nickname":"Lenhador da Fronteira","Transform":{"posX":0,"posY":0,"posZ":0,"rotX":0,"rotY":180,"rotZ":180,"scaleX":1,"scaleY":1,"scaleZ":1}},{"CardID":123,"Name":"card","Nickname":"Aprendiz de Engenho","Transform":{"posX":0,"posY":0,"posZ":0,"rotX":0,"rotY":180,"rotZ":180,"scaleX":1,"scaleY":1,"scaleZ":1}},{"CardID":124,"Name":"card","Nickname":"Sentinela de Pedra Escura","Transform":{"posX":0,"posY":0,"posZ":0,"rotX":0,"rotY":180,"rotZ":180,"scaleX":1,"scaleY":1,"scaleZ":1}},{"CardID":125,"Name":"card","Nickname":"Mestre da Moeda Antiga","Transform":{"posX":0,"posY":0,"posZ":0,"rotX":0,"rotY":180,"rotZ":180,"scaleX":1,"scaleY":1,"scaleZ":1}},{"CardID":126,"Name":"card","Nickname":"Artilheiro de Brasa Lenta","Transform":{"posX":0,"posY":0,"posZ":0,"rotX":0,"rotY":180,"rotZ":180,"scaleX":1,"scaleY":1,"scaleZ":1}},{"CardID":127,"Name":"card","Nickname":"Arqueiro da Torre Azul","Transform":{"posX":0,"posY":0,"posZ":0,"rotX":0,"rotY":180,"rotZ":180,"scaleX":1,"scaleY":1,"scaleZ":1}},{"CardID":128,"Name":"card","Nickname":"Arqueiro de Repetição","Transform":{"posX":0,"posY":0,"posZ":0,"rotX":0,"rotY":180,"rotZ":180,"scaleX":1,"scaleY":1,"scaleZ":1}},{"CardID":129,"Name":"card","Nickname":"Executor Ardente","Transform":{"posX":0,"posY":0,"posZ":0,"rotX":0,"rotY":180,"rotZ":180,"scaleX":1,"scaleY":1,"scaleZ":1}},{"CardID":130,"Name":"card","Nickname":"Patrulheiro de Rotas Fortificadas","Transform":{"posX":0,"posY":0,"posZ":0,"rotX":0,"rotY":180,"rotZ":180,"scaleX":1,"scaleY":1,"scaleZ":1}},{"CardID":131,"Name":"card","Nickname":"Batedor da Primeira Companhia","Transform":{"posX":0,"posY":0,"posZ":0,"rotX":0,"rotY":180,"rotZ":180,"scaleX":1,"scaleY":1,"scaleZ":1}},{"CardID":132,"Name":"card","Nickname":"Oficial da Patrulha Costeira","Transform":{"posX":0,"posY":0,"posZ":0,"rotX":0,"rotY":180,"rotZ":180,"scaleX":1,"scaleY":1,"scaleZ":1}},{"CardID":133,"Name":"card","Nickname":"Cavalaria de Pedra Curva","Transform":{"posX":0,"posY":0,"posZ":0,"rotX":0,"rotY":180,"rotZ":180,"scaleX":1,"scaleY":1,"scaleZ":1}},{"CardID":134,"Name":"card","Nickname":"Batedor das Planícies","Transform":{"posX":0,"posY":0,"posZ":0,"rotX":0,"rotY":180,"rotZ":180,"scaleX":1,"scaleY":1,"scaleZ":1}},{"CardID":135,"Name":"card","Nickname":"Orador da Assembleia","Transform":{"posX":0,"posY":0,"posZ":0,"rotX":0,"rotY":180,"rotZ":180,"scaleX":1,"scaleY":1,"scaleZ":1}},{"CardID":136,"Name":"card","Nickname":"Gestor de Reforços","Transform":{"posX":0,"posY":0,"posZ":0,"rotX":0,"rotY":180,"rotZ":180,"scaleX":1,"scaleY":1,"scaleZ":1}},{"CardID":137,"Name":"card","Nickname":"Placas Reforçadas de Cerco","Transform":{"posX":0,"posY":0,"posZ":0,"rotX":0,"rotY":180,"rotZ":180,"scaleX":1,"scaleY":1,"scaleZ":1}},{"CardID":138,"Name":"card","Nickname":"Armadura de Grade Dourada","Transform":{"posX":0,"posY":0,"posZ":0,"rotX":0,"rotY":180,"rotZ":180,"scaleX":1,"scaleY":1,"scaleZ":1}},{"CardID":139,"Name":"card","Nickname":"Armadura Modelo \"Mamute\"","Transform":{"posX":0,"posY":0,"posZ":0,"rotX":0,"rotY":180,"rotZ":180,"scaleX":1,"scaleY":1,"scaleZ":1}},{"CardID":140,"Name":"card","Nickname":"Ordem de Destruição","Transform":{"posX":0,"posY":0,"posZ":0,"rotX":0,"rotY":180,"rotZ":180,"scaleX":1,"scaleY":1,"scaleZ":1}},{"CardID":141,"Name":"card","Nickname":"Foco de Ação Rápida","Transform":{"posX":0,"posY":0,"posZ":0,"rotX":0,"rotY":180,"rotZ":180,"scaleX":1,"scaleY":1,"scaleZ":1}},{"CardID":142,"Name":"card","Nickname":"Forja dos Campeões","Transform":{"posX":0,"posY":0,"posZ":0,"rotX":0,"rotY":180,"rotZ":180,"scaleX":1,"scaleY":1,"scaleZ":1}},{"CardID":143,"Name":"card","Nickname":"Espada do Comando","Transform":{"posX":0,"posY":0,"posZ":0,"rotX":0,"rotY":180,"rotZ":180,"scaleX":1,"scaleY":1,"scaleZ":1}},{"CardID":144,"Name":"card","Nickname":"Escudo da Capital","Transform":{"posX":0,"posY":0,"posZ":0,"rotX":0,"rotY":180,"rotZ":180,"scaleX":1,"scaleY":1,"scaleZ":1}},{"CardID":145,"Name":"card","Nickname":"Elos de Honra","Transform":{"posX":0,"posY":0,"posZ":0,"rotX":0,"rotY":180,"rotZ":180,"scaleX":1,"scaleY":1,"scaleZ":1}},{"CardID":146,"Name":"card","Nickname":"Dominância Coordenada","Transform":{"posX":0,"posY":0,"posZ":0,"rotX":0,"rotY":180,"rotZ":180,"scaleX":1,"scaleY":1,"scaleZ":1}},{"CardID":147,"Name":"card","Nickname":"Reforço Temporário","Transform":{"posX":0,"posY":0,"posZ":0,"rotX":0,"rotY":180,"rotZ":180,"scaleX":1,"scaleY":1,"scaleZ":1}},{"CardID":200,"Name":"card","Nickname":"Peso da Estratégia","Transform":{"posX":0,"posY":0,"posZ":0,"rotX":0,"rotY":180,"rotZ":180,"scaleX":1,"scaleY":1,"scaleZ":1}},{"CardID":201,"Name":"card","Nickname":"Doutrina do Cerco","Transform":{"posX":0,"posY":0,"posZ":0,"rotX":0,"rotY":180,"rotZ":180,"scaleX":1,"scaleY":1,"scaleZ":1}},{"CardID":202,"Name":"card","Nickname":"Engendro Carmesim","Transform":{"posX":0,"posY":0,"posZ":0,"rotX":0,"rotY":180,"rotZ":180,"scaleX":1,"scaleY":1,"scaleZ":1}},{"CardID":203,"Name":"card","Nickname":"Portador do Silêncio Vermelho","Transform":{"posX":0,"posY":0,"posZ":0,"rotX":0,"rotY":180,"rotZ":180,"scaleX":1,"scaleY":1,"scaleZ":1}},{"CardID":204,"Name":"card","Nickname":"Berserk em armadura \"Mamute\"","Transform":{"posX":0,"posY":0,"posZ":0,"rotX":0,"rotY":180,"rotZ":180,"scaleX":1,"scaleY":1,"scaleZ":1}},{"CardID":205,"Name":"card","Nickname":"Silenciador","Transform":{"posX":0,"posY":0,"posZ":0,"rotX":0,"rotY":180,"rotZ":180,"scaleX":1,"scaleY":1,"scaleZ":1}},{"CardID":206,"Name":"card","Nickname":"Especialista Alquímico de Retaguarda","Transform":{"posX":0,"posY":0,"posZ":0,"rotX":0,"rotY":180,"rotZ":180,"scaleX":1,"scaleY":1,"scaleZ":1}},{"CardID":207,"Name":"card","Nickname":"Especialista em Demolição Controlada","Transform":{"posX":0,"posY":0,"posZ":0,"rotX":0,"rotY":180,"rotZ":180,"scaleX":1,"scaleY":1,"scaleZ":1}},{"CardID":208,"Name":"card","Nickname":"Escudeiro Pesado de Linha Frontal","Transform":{"posX":0,"posY":0,"posZ":0,"rotX":0,"rotY":180,"rotZ":180,"scaleX":1,"scaleY":1,"scaleZ":1}},{"CardID":209,"Name":"card","Nickname":"Auxiliar Alquímico de Batalhão","Transform":{"posX":0,"posY":0,"posZ":0,"rotX":0,"rotY":180,"rotZ":180,"scaleX":1,"scaleY":1,"scaleZ":1}},{"CardID":210,"Name":"card","Nickname":"Alquimista da Bruma Violeta","Transform":{"posX":0,"posY":0,"posZ":0,"rotX":0,"rotY":180,"rotZ":180,"scaleX":1,"scaleY":1,"scaleZ":1}},{"CardID":211,"Name":"card","Nickname":"Escudeiro da Muralha Norte","Transform":{"posX":0,"posY":0,"posZ":0,"rotX":0,"rotY":180,"rotZ":180,"scaleX":1,"scaleY":1,"scaleZ":1}},{"CardID":212,"Name":"card","Nickname":"Ferreiro de Linha Frontal","Transform":{"posX":0,"posY":0,"posZ":0,"rotX":0,"rotY":180,"rotZ":180,"scaleX":1,"scaleY":1,"scaleZ":1}},{"CardID":213,"Name":"card","Nickname":"Veterano do Cerco de Gash","Transform":{"posX":0,"posY":0,"posZ":0,"rotX":0,"rotY":180,"rotZ":180,"scaleX":1,"scaleY":1,"scaleZ":1}},{"CardID":214,"Name":"card","Nickname":"Mestre de Formação Tática","Transform":{"posX":0,"posY":0,"posZ":0,"rotX":0,"rotY":180,"rotZ":180,"scaleX":1,"scaleY":1,"scaleZ":1}},{"CardID":215,"Name":"card","Nickname":"Sabotador de Túnel Curvo","Transform":{"posX":0,"posY":0,"posZ":0,"rotX":0,"rotY":180,"rotZ":180,"scaleX":1,"scaleY":1,"scaleZ":1}},{"CardID":216,"Name":"card","Nickname":"Sargento de Treinamento","Transform":{"posX":0,"posY":0,"posZ":0,"rotX":0,"rotY":180,"rotZ":180,"scaleX":1,"scaleY":1,"scaleZ":1}},{"CardID":217,"Name":"card","Nickname":"Infante de Couraça Leve","Transform":{"posX":0,"posY":0,"posZ":0,"rotX":0,"rotY":180,"rotZ":180,"scaleX":1,"scaleY":1,"scaleZ":1}},{"CardID":218,"Name":"card","Nickname":"Veterano da Muralha Sul","Transform":{"posX":0,"posY":0,"posZ":0,"rotX":0,"rotY":180,"rotZ":180,"scaleX":1,"scaleY":1,"scaleZ":1}},{"CardID":219,"Name":"card","Nickname":"Guarda da Ponte Leste","Transform":{"posX":0,"posY":0,"posZ":0,"rotX":0,"rotY":180,"rotZ":180,"scaleX":1,"scaleY":1,"scaleZ":1}},{"CardID":220,"Name":"card","Nickname":"Engenheiro de Suporte","Transform":{"posX":0,"posY":0,"posZ":0,"rotX":0,"rotY":180,"rotZ":180,"scaleX":1,"scaleY":1,"scaleZ":1}},{"CardID":221,"Name":"card","Nickname":"Médico de Retaguarda","Transform":{"posX":0,"posY":0,"posZ":0,"rotX":0,"rotY":180,"rotZ":180,"scaleX":1,"scaleY":1,"scaleZ":1}},{"CardID":222,"Name":"card","Nickname":"Aspirante da Guarda","Transform":{"posX":0,"posY":0,"posZ":0,"rotX":0,"rotY":180,"rotZ":180,"scaleX":1,"scaleY":1,"scaleZ":1}},{"CardID":223,"Name":"card","Nickname":"Avaliador da Legião","Transform":{"posX":0,"posY":0,"posZ":0,"rotX":0,"rotY":180,"rotZ":180,"scaleX":1,"scaleY":1,"scaleZ":1}},{"CardID":224,"Name":"card","Nickname":"Capitão dos Muros","Transform":{"posX":0,"posY":0,"posZ":0,"rotX":0,"rotY":180,"rotZ":180,"scaleX":1,"scaleY":1,"scaleZ":1}},{"CardID":225,"Name":"card","Nickname":"Ouvidor de Linha","Transform":{"posX":0,"posY":0,"posZ":0,"rotX":0,"rotY":180,"rotZ":180,"scaleX":1,"scaleY":1,"scaleZ":1}},{"CardID":226,"Name":"card","Nickname":"Guarda de Cerco","Transform":{"posX":0,"posY":0,"posZ":0,"rotX":0,"rotY":180,"rotZ":180,"scaleX":1,"scaleY":1,"scaleZ":1}},{"CardID":227,"Name":"card","Nickname":"Titã de Ferro ","Transform":{"posX":0,"posY":0,"posZ":0,"rotX":0,"rotY":180,"rotZ":180,"scaleX":1,"scaleY":1,"scaleZ":1}},{"CardID":228,"Name":"card","Nickname":"Artífice Real","Transform":{"posX":0,"posY":0,"posZ":0,"rotX":0,"rotY":180,"rotZ":180,"scaleX":1,"scaleY":1,"scaleZ":1}},{"CardID":229,"Name":"card","Nickname":"Operário de Fortificação","Transform":{"posX":0,"posY":0,"posZ":0,"rotX":0,"rotY":180,"rotZ":180,"scaleX":1,"scaleY":1,"scaleZ":1}},{"CardID":230,"Name":"card","Nickname":"Erveiro das Planícies","Transform":{"posX":0,"posY":0,"posZ":0,"rotX":0,"rotY":180,"rotZ":180,"scaleX":1,"scaleY":1,"scaleZ":1}},{"CardID":231,"Name":"card","Nickname":"Engenheiro de Linha","Transform":{"posX":0,"posY":0,"posZ":0,"rotX":0,"rotY":180,"rotZ":180,"scaleX":1,"scaleY":1,"scaleZ":1}},{"CardID":232,"Name":"card","Nickname":"Ferreiro de Guerra","Transform":{"posX":0,"posY":0,"posZ":0,"rotX":0,"rotY":180,"rotZ":180,"scaleX":1,"scaleY":1,"scaleZ":1}},{"CardID":233,"Name":"card","Nickname":"Camponês","Transform":{"posX":0,"posY":0,"posZ":0,"rotX":0,"rotY":180,"rotZ":180,"scaleX":1,"scaleY":1,"scaleZ":1}},{"CardID":234,"Name":"card","Nickname":"Instrutor Auxiliar da Torre Alva","Transform":{"posX":0,"posY":0,"posZ":0,"rotX":0,"rotY":180,"rotZ":180,"scaleX":1,"scaleY":1,"scaleZ":1}},{"CardID":235,"Name":"card","Nickname":"Estudante da Biblioteca Marcial","Transform":{"posX":0,"posY":0,"posZ":0,"rotX":0,"rotY":180,"rotZ":180,"scaleX":1,"scaleY":1,"scaleZ":1}},{"CardID":236,"Name":"card","Nickname":"Alquimista da Vanguarda Real","Transform":{"posX":0,"posY":0,"posZ":0,"rotX":0,"rotY":180,"rotZ":180,"scaleX":1,"scaleY":1,"scaleZ":1}},{"CardID":237,"Name":"card","Nickname":"Recrutador de Voluntários","Transform":{"posX":0,"posY":0,"posZ":0,"rotX":0,"rotY":180,"rotZ":180,"scaleX":1,"scaleY":1,"scaleZ":1}},{"CardID":238,"Name":"card","Nickname":"Escolástico da Torre Alva","Transform":{"posX":0,"posY":0,"posZ":0,"rotX":0,"rotY":180,"rotZ":180,"scaleX":1,"scaleY":1,"scaleZ":1}},{"CardID":239,"Name":"card","Nickname":"Escolástico de Campanha","Transform":{"posX":0,"posY":0,"posZ":0,"rotX":0,"rotY":180,"rotZ":180,"scaleX":1,"scaleY":1,"scaleZ":1}},{"CardID":240,"Name":"card","Nickname":"Tutor da Torre Cívica","Transform":{"posX":0,"posY":0,"posZ":0,"rotX":0,"rotY":180,"rotZ":180,"scaleX":1,"scaleY":1,"scaleZ":1}},{"CardID":241,"Name":"card","Nickname":"Grito de Lealdade","Transform":{"posX":0,"posY":0,"posZ":0,"rotX":0,"rotY":180,"rotZ":180,"scaleX":1,"scaleY":1,"scaleZ":1}},{"CardID":242,"Name":"card","Nickname":"Contraordem Total","Transform":{"posX":0,"posY":0,"posZ":0,"rotX":0,"rotY":180,"rotZ":180,"scaleX":1,"scaleY":1,"scaleZ":1}},{"CardID":243,"Name":"card","Nickname":"Reforço Imediato","Transform":{"posX":0,"posY":0,"posZ":0,"rotX":0,"rotY":180,"rotZ":180,"scaleX":1,"scaleY":1,"scaleZ":1}},{"CardID":244,"Name":"card","Nickname":"Contracorrente","Transform":{"posX":0,"posY":0,"posZ":0,"rotX":0,"rotY":180,"rotZ":180,"scaleX":1,"scaleY":1,"scaleZ":1}},{"CardID":245,"Name":"card","Nickname":"Fim da Linha","Transform":{"posX":0,"posY":0,"posZ":0,"rotX":0,"rotY":180,"rotZ":180,"scaleX":1,"scaleY":1,"scaleZ":1}},{"CardID":246,"Name":"card","Nickname":"Ritual do Sangue Primordial","Transform":{"posX":0,"posY":0,"posZ":0,"rotX":0,"rotY":180,"rotZ":180,"scaleX":1,"scaleY":1,"scaleZ":1}},{"CardID":247,"Name":"card","Nickname":"Comando da Última Linhagem","Transform":{"posX":0,"posY":0,"posZ":0,"rotX":0,"rotY":180,"rotZ":180,"scaleX":1,"scaleY":1,"scaleZ":1}},{"CardID":300,"Name":"card","Nickname":"Intervenção Coordenada","Transform":{"posX":0,"posY":0,"posZ":0,"rotX":0,"rotY":180,"rotZ":180,"scaleX":1,"scaleY":1,"scaleZ":1}},{"CardID":301,"Name":"card","Nickname":"Ordem do Alto-Comando","Transform":{"posX":0,"posY":0,"posZ":0,"rotX":0,"rotY":180,"rotZ":180,"scaleX":1,"scaleY":1,"scaleZ":1}},{"CardID":302,"Name":"card","Nickname":"Plano de Contingência","Transform":{"posX":0,"posY":0,"posZ":0,"rotX":0,"rotY":180,"rotZ":180,"scaleX":1,"scaleY":1,"scaleZ":1}},{"CardID":303,"Name":"card","Nickname":"Colapso Estrutural","Transform":{"posX":0,"posY":0,"posZ":0,"rotX":0,"rotY":180,"rotZ":180,"scaleX":1,"scaleY":1,"scaleZ":1}},{"CardID":304,"Name":"card","Nickname":"Último Estandarte","Transform":{"posX":0,"posY":0,"posZ":0,"rotX":0,"rotY":180,"rotZ":180,"scaleX":1,"scaleY":1,"scaleZ":1}},{"CardID":305,"Name":"card","Nickname":"Ponto de Ruptura","Transform":{"posX":0,"posY":0,"posZ":0,"rotX":0,"rotY":180,"rotZ":180,"scaleX":1,"scaleY":1,"scaleZ":1}},{"CardID":306,"Name":"card","Nickname":"Sinal Codificado","Transform":{"posX":0,"posY":0,"posZ":0,"rotX":0,"rotY":180,"rotZ":180,"scaleX":1,"scaleY":1,"scaleZ":1}},{"CardID":307,"Name":"card","Nickname":"Última Retomada","Transform":{"posX":0,"posY":0,"posZ":0,"rotX":0,"rotY":180,"rotZ":180,"scaleX":1,"scaleY":1,"scaleZ":1}},{"CardID":308,"Name":"card","Nickname":"Revogar Ordem","Transform":{"posX":0,"posY":0,"posZ":0,"rotX":0,"rotY":180,"rotZ":180,"scaleX":1,"scaleY":1,"scaleZ":1}},{"CardID":309,"Name":"card","Nickname":"Ajuda Mútua","Transform":{"posX":0,"posY":0,"posZ":0,"rotX":0,"rotY":180,"rotZ":180,"scaleX":1,"scaleY":1,"scaleZ":1}},{"CardID":310,"Name":"card","Nickname":"Intelecto de Brightwill","Transform":{"posX":0,"posY":0,"posZ":0,"rotX":0,"rotY":180,"rotZ":180,"scaleX":1,"scaleY":1,"scaleZ":1}},{"CardID":311,"Name":"card","Nickname":"Estabilização de Linha","Transform":{"posX":0,"posY":0,"posZ":0,"rotX":0,"rotY":180,"rotZ":180,"scaleX":1,"scaleY":1,"scaleZ":1}},{"CardID":312,"Name":"card","Nickname":"Portal de Translocação","Transform":{"posX":0,"posY":0,"posZ":0,"rotX":0,"rotY":180,"rotZ":180,"scaleX":1,"scaleY":1,"scaleZ":1}},{"CardID":313,"Name":"card","Nickname":"Linha de Suprimentos","Transform":{"posX":0,"posY":0,"posZ":0,"rotX":0,"rotY":180,"rotZ":180,"scaleX":1,"scaleY":1,"scaleZ":1}},{"CardID":314,"Name":"card","Nickname":"Protocolo de Guerra","Transform":{"posX":0,"posY":0,"posZ":0,"rotX":0,"rotY":180,"rotZ":180,"scaleX":1,"scaleY":1,"scaleZ":1}},{"CardID":315,"Name":"card","Nickname":"Domínio Fortificado","Transform":{"posX":0,"posY":0,"posZ":0,"rotX":0,"rotY":180,"rotZ":180,"scaleX":1,"scaleY":1,"scaleZ":1}},{"CardID":316,"Name":"card","Nickname":"Barreira Vigilante","Transform":{"posX":0,"posY":0,"posZ":0,"rotX":0,"rotY":180,"rotZ":180,"scaleX":1,"scaleY":1,"scaleZ":1}},{"CardID":317,"Name":"card","Nickname":"Zona de Rebelião","Transform":{"posX":0,"posY":0,"posZ":0,"rotX":0,"rotY":180,"rotZ":180,"scaleX":1,"scaleY":1,"scaleZ":1}},{"CardID":318,"Name":"card","Nickname":"Zona Fortificada","Transform":{"posX":0,"posY":0,"posZ":0,"rotX":0,"rotY":180,"rotZ":180,"scaleX":1,"scaleY":1,"scaleZ":1}},{"CardID":319,"Name":"card","Nickname":"Refúgio Popular","Transform":{"posX":0,"posY":0,"posZ":0,"rotX":0,"rotY":180,"rotZ":180,"scaleX":1,"scaleY":1,"scaleZ":1}},{"CardID":320,"Name":"card","Nickname":"Comando Rígido","Transform":{"posX":0,"posY":0,"posZ":0,"rotX":0,"rotY":180,"rotZ":180,"scaleX":1,"scaleY":1,"scaleZ":1}},{"CardID":321,"Name":"card","Nickname":"Poça Congelada","Transform":{"posX":0,"posY":0,"posZ":0,"rotX":0,"rotY":180,"rotZ":180,"scaleX":1,"scaleY":1,"scaleZ":1}},{"CardID":322,"Name":"card","Nickname":"Pressão Total","Transform":{"posX":0,"posY":0,"posZ":0,"rotX":0,"rotY":180,"rotZ":180,"scaleX":1,"scaleY":1,"scaleZ":1}}],"CustomDeck":{"1":{"FaceUrl":"https://firebasestorage.googleapis.com/v0/b/card-maker-74ec3.appspot.com/o/images%2FNY3nvvhhyAUznBnaYs0SFEQD0Ge2%2FTTSFiles%2Fjrt2r8yLe1YMYZ7KDSvo_r9k76bDi22HIgchXFFkY_0.png?alt=media&token=5c0b4754-a9a3-4822-8e30-d74b7e3b5322","BackUrl":"https://firebasestorage.googleapis.com/v0/b/card-maker-74ec3.appspot.com/o/images%2FNY3nvvhhyAUznBnaYs0SFEQD0Ge2%2FTTSFiles%2Fjrt2r8yLe1YMYZ7KDSvo_back_r9k76bDi22HIgchXFFkY_0.png?alt=media&token=dff09012-90bd-44f2-8eae-9e32090234fd","NumWidth":8,"NumHeight":6,"BackIsHidden":true,"UniqueBack":false,"Type":0},"2":{"FaceUrl":"https://firebasestorage.googleapis.com/v0/b/card-maker-74ec3.appspot.com/o/images%2FNY3nvvhhyAUznBnaYs0SFEQD0Ge2%2FTTSFiles%2Fjrt2r8yLe1YMYZ7KDSvo_r9k76bDi22HIgchXFFkY_1.png?alt=media&token=ef8d2ae2-9348-4515-b490-dfb3e3bdc46b","BackUrl":"https://firebasestorage.googleapis.com/v0/b/card-maker-74ec3.appspot.com/o/images%2FNY3nvvhhyAUznBnaYs0SFEQD0Ge2%2FTTSFiles%2Fjrt2r8yLe1YMYZ7KDSvo_back_r9k76bDi22HIgchXFFkY_1.png?alt=media&token=0f157231-0516-4ee2-b5f3-d22d3ffd6f32","NumWidth":8,"NumHeight":6,"BackIsHidden":true,"UniqueBack":false,"Type":0},"3":{"FaceUrl":"https://firebasestorage.googleapis.com/v0/b/card-maker-74ec3.appspot.com/o/images%2FNY3nvvhhyAUznBnaYs0SFEQD0Ge2%2FTTSFiles%2Fjrt2r8yLe1YMYZ7KDSvo_r9k76bDi22HIgchXFFkY_2.png?alt=media&token=22160691-ce77-4d2a-a8e1-246c7971951b","BackUrl":"https://firebasestorage.googleapis.com/v0/b/card-maker-74ec3.appspot.com/o/images%2FNY3nvvhhyAUznBnaYs0SFEQD0Ge2%2FTTSFiles%2Fjrt2r8yLe1YMYZ7KDSvo_back_r9k76bDi22HIgchXFFkY_2.png?alt=media&token=7746fa71-cd6d-4895-8af4-a4fb5cf74fe2","NumWidth":8,"NumHeight":6,"BackIsHidden":true,"UniqueBack":false,"Type":0}}},{"Name":"Deck","Nickname":"Deck Locais","Description":"","LuaScript":"","Transform":{"posX":3,"posY":0,"posZ":0,"rotX":0,"rotY":180,"rotZ":180,"scaleX":0.9097673160144049,"scaleY":1,"scaleZ":0.9097673160144049},"DeckIDs":[100,101,102,103,104,105,106,107,108,109,110,111,112,113,114,115,116,117,118,119,120,121,122,123,124,125,126,127,200,201,202,203],"ContainedObjects":[{"CardID":100,"Name":"card","Nickname":"Vila de Hammenhart","Description":"","Transform":{"posX":0,"posY":0,"posZ":0,"rotX":0,"rotY":180,"rotZ":180,"scaleX":1,"scaleY":1,"scaleZ":1}},{"CardID":101,"Name":"card","Nickname":"Feira Coberta de Darnor","Transform":{"posX":0,"posY":0,"posZ":0,"rotX":0,"rotY":180,"rotZ":180,"scaleX":1,"scaleY":1,"scaleZ":1}},{"CardID":102,"Name":"card","Nickname":"Posto de Guarda de Kress","Transform":{"posX":0,"posY":0,"posZ":0,"rotX":0,"rotY":180,"rotZ":180,"scaleX":1,"scaleY":1,"scaleZ":1}},{"CardID":103,"Name":"card","Nickname":"Cidade","Transform":{"posX":0,"posY":0,"posZ":0,"rotX":0,"rotY":180,"rotZ":180,"scaleX":1,"scaleY":1,"scaleZ":1}},{"CardID":104,"Name":"card","Nickname":"Praça dos Estandartes","Transform":{"posX":0,"posY":0,"posZ":0,"rotX":0,"rotY":180,"rotZ":180,"scaleX":1,"scaleY":1,"scaleZ":1}},{"CardID":105,"Name":"card","Nickname":"Fazenda de Barro Branco","Transform":{"posX":0,"posY":0,"posZ":0,"rotX":0,"rotY":180,"rotZ":180,"scaleX":1,"scaleY":1,"scaleZ":1}},{"CardID":106,"Name":"card","Nickname":"Aldeia de Bravura","Transform":{"posX":0,"posY":0,"posZ":0,"rotX":0,"rotY":180,"rotZ":180,"scaleX":1,"scaleY":1,"scaleZ":1}},{"CardID":107,"Name":"card","Nickname":"Bairro dos Canais Baixos","Transform":{"posX":0,"posY":0,"posZ":0,"rotX":0,"rotY":180,"rotZ":180,"scaleX":1,"scaleY":1,"scaleZ":1}},{"CardID":108,"Name":"card","Nickname":"Círculo de Convergência Alquímica","Transform":{"posX":0,"posY":0,"posZ":0,"rotX":0,"rotY":180,"rotZ":180,"scaleX":1,"scaleY":1,"scaleZ":1}},{"CardID":109,"Name":"card","Nickname":"Portão das Correntes de Prata","Transform":{"posX":0,"posY":0,"posZ":0,"rotX":0,"rotY":180,"rotZ":180,"scaleX":1,"scaleY":1,"scaleZ":1}},{"CardID":110,"Name":"card","Nickname":"Distrito dos Nomes Perdidos","Transform":{"posX":0,"posY":0,"posZ":0,"rotX":0,"rotY":180,"rotZ":180,"scaleX":1,"scaleY":1,"scaleZ":1}},{"CardID":111,"Name":"card","Nickname":"Salão das Guildas Silenciosas","Transform":{"posX":0,"posY":0,"posZ":0,"rotX":0,"rotY":180,"rotZ":180,"scaleX":1,"scaleY":1,"scaleZ":1}},{"CardID":112,"Name":"card","Nickname":"Oficina de Cerco Suldente","Transform":{"posX":0,"posY":0,"posZ":0,"rotX":0,"rotY":180,"rotZ":180,"scaleX":1,"scaleY":1,"scaleZ":1}},{"CardID":113,"Name":"card","Nickname":"Bastião de Comando Avançado","Transform":{"posX":0,"posY":0,"posZ":0,"rotX":0,"rotY":180,"rotZ":180,"scaleX":1,"scaleY":1,"scaleZ":1}},{"CardID":114,"Name":"card","Nickname":"Laboratório do Sangue Fervente","Transform":{"posX":0,"posY":0,"posZ":0,"rotX":0,"rotY":180,"rotZ":180,"scaleX":1,"scaleY":1,"scaleZ":1}},{"CardID":115,"Name":"card","Nickname":"Túmulo dos Fundadores de Strom","Transform":{"posX":0,"posY":0,"posZ":0,"rotX":0,"rotY":180,"rotZ":180,"scaleX":1,"scaleY":1,"scaleZ":1}},{"CardID":116,"Name":"card","Nickname":"Reduto das Escamas Queimadas","Transform":{"posX":0,"posY":0,"posZ":0,"rotX":0,"rotY":180,"rotZ":180,"scaleX":1,"scaleY":1,"scaleZ":1}},{"CardID":117,"Name":"card","Nickname":"Salão de Guerra de Brightwill","Transform":{"posX":0,"posY":0,"posZ":0,"rotX":0,"rotY":180,"rotZ":180,"scaleX":1,"scaleY":1,"scaleZ":1}},{"CardID":118,"Name":"card","Nickname":"Câmara dos Juramentos","Transform":{"posX":0,"posY":0,"posZ":0,"rotX":0,"rotY":180,"rotZ":180,"scaleX":1,"scaleY":1,"scaleZ":1}},{"CardID":119,"Name":"card","Nickname":"Centro de Arbitragem de Strom","Transform":{"posX":0,"posY":0,"posZ":0,"rotX":0,"rotY":180,"rotZ":180,"scaleX":1,"scaleY":1,"scaleZ":1}},{"CardID":120,"Name":"card","Nickname":"Palácio do Sol","Transform":{"posX":0,"posY":0,"posZ":0,"rotX":0,"rotY":180,"rotZ":180,"scaleX":1,"scaleY":1,"scaleZ":1}},{"CardID":121,"Name":"card","Nickname":"Aldeia de Bravura","Transform":{"posX":0,"posY":0,"posZ":0,"rotX":0,"rotY":180,"rotZ":180,"scaleX":1,"scaleY":1,"scaleZ":1}},{"CardID":122,"Name":"card","Nickname":"Trincheiras de Fervor Quebrado","Transform":{"posX":0,"posY":0,"posZ":0,"rotX":0,"rotY":180,"rotZ":180,"scaleX":1,"scaleY":1,"scaleZ":1}},{"CardID":123,"Name":"card","Nickname":"Campo de Cultivo Ascendente","Transform":{"posX":0,"posY":0,"posZ":0,"rotX":0,"rotY":180,"rotZ":180,"scaleX":1,"scaleY":1,"scaleZ":1}},{"CardID":124,"Name":"card","Nickname":"Mina do Martelo Cego","Transform":{"posX":0,"posY":0,"posZ":0,"rotX":0,"rotY":180,"rotZ":180,"scaleX":1,"scaleY":1,"scaleZ":1}},{"CardID":125,"Name":"card","Nickname":"Capela do Dragão Dourado","Transform":{"posX":0,"posY":0,"posZ":0,"rotX":0,"rotY":180,"rotZ":180,"scaleX":1,"scaleY":1,"scaleZ":1}},{"CardID":126,"Name":"card","Nickname":"Ruínas de Vhan-Storm","Transform":{"posX":0,"posY":0,"posZ":0,"rotX":0,"rotY":180,"rotZ":180,"scaleX":1,"scaleY":1,"scaleZ":1}},{"CardID":127,"Name":"card","Nickname":"Rota da Muralha Leste","Transform":{"posX":0,"posY":0,"posZ":0,"rotX":0,"rotY":180,"rotZ":180,"scaleX":1,"scaleY":1,"scaleZ":1}},{"CardID":200,"Name":"card","Nickname":"Quartel das Emanações","Transform":{"posX":0,"posY":0,"posZ":0,"rotX":0,"rotY":180,"rotZ":180,"scaleX":1,"scaleY":1,"scaleZ":1}},{"CardID":201,"Name":"card","Nickname":"Capela de Grurom","Transform":{"posX":0,"posY":0,"posZ":0,"rotX":0,"rotY":180,"rotZ":180,"scaleX":1,"scaleY":1,"scaleZ":1}},{"CardID":202,"Name":"card","Nickname":"Arco da Aurora","Transform":{"posX":0,"posY":0,"posZ":0,"rotX":0,"rotY":180,"rotZ":180,"scaleX":1,"scaleY":1,"scaleZ":1}},{"CardID":203,"Name":"card","Nickname":"Cruzamento da Espada Cega","Transform":{"posX":0,"posY":0,"posZ":0,"rotX":0,"rotY":180,"rotZ":180,"scaleX":1,"scaleY":1,"scaleZ":1}}],"CustomDeck":{"1":{"FaceUrl":"https://firebasestorage.googleapis.com/v0/b/card-maker-74ec3.appspot.com/o/images%2FNY3nvvhhyAUznBnaYs0SFEQD0Ge2%2FTTSFiles%2Fjrt2r8yLe1YMYZ7KDSvo_g1BqhJ5KLaE218xz0NdC_0.png?alt=media&token=177bc1c0-6035-4618-a6fa-d35d6d6ea456","BackUrl":"https://firebasestorage.googleapis.com/v0/b/card-maker-74ec3.appspot.com/o/images%2FNY3nvvhhyAUznBnaYs0SFEQD0Ge2%2FTTSFiles%2Fjrt2r8yLe1YMYZ7KDSvo_back_g1BqhJ5KLaE218xz0NdC_0.png?alt=media&token=17d8a96c-22c1-4de9-80e9-060f0944e113","NumWidth":4,"NumHeight":7,"BackIsHidden":true,"UniqueBack":false,"Type":0},"2":{"FaceUrl":"https://firebasestorage.googleapis.com/v0/b/card-maker-74ec3.appspot.com/o/images%2FNY3nvvhhyAUznBnaYs0SFEQD0Ge2%2FTTSFiles%2Fjrt2r8yLe1YMYZ7KDSvo_g1BqhJ5KLaE218xz0NdC_1.png?alt=media&token=a64063a7-1dd9-420e-9661-dbfeed55236e","BackUrl":"https://firebasestorage.googleapis.com/v0/b/card-maker-74ec3.appspot.com/o/images%2FNY3nvvhhyAUznBnaYs0SFEQD0Ge2%2FTTSFiles%2Fjrt2r8yLe1YMYZ7KDSvo_back_g1BqhJ5KLaE218xz0NdC_1.png?alt=media&token=b7ab2069-d2ec-4b01-99c5-fc2f7af6a0f2","NumWidth":4,"NumHeight":7,"BackIsHidden":true,"UniqueBack":false,"Type":0}}}]}